q/api/__init__.py
q/api/__init__.pyi
q/api/append.py
q/api/errors.py
q/api/queue.py
q/api/read.py
q/api/write.py
q/api/impl/__init__.py
q/api/impl/empty.py
q/api/impl/simple.py
q/api/ops/__init__.py
q/api/ops/__init__.pyi
q/api/ops/append_bounding.py
q/api/ops/bounding.py
q/api/ops/interleaving.py
q/api/ops/merging.py
q/api/ops/splitting.py
q/api/ops/teeing.py
queue_api-0.1.7.dist-info/METADATA
queue_api-0.1.7.dist-info/WHEEL
queue_api-0.1.7.dist-info/top_level.txt
queue_api-0.1.7.dist-info/RECORD
