Metadata-Version: 2.1
Name: queue-api
Version: 0.1.7
Summary: ABC for asynchronous, point-readable, exception-free read/write queues
Author-email: Marcel Claramunt <marcel@moveread.com>
Project-URL: repo, https://github.com/marciclabas/python-storage.git
Requires-Python: >=3.10
Requires-Dist: haskellian
Requires-Dist: lazy-loader
